tagpatch/__init__.py
tagpatch/__main__.py
tagpatch/types.py
tagpatch/utils.py
tagpatch/patches/__init__.py
tagpatch/patches/artist_name.py
tagpatch/patches/download_lrc.py
tagpatch/patches/embed_lrc.py
tagpatch/patches/patch.py
tagpatch-0.1.4.dist-info/METADATA
tagpatch-0.1.4.dist-info/WHEEL
tagpatch-0.1.4.dist-info/entry_points.txt
tagpatch-0.1.4.dist-info/licenses/LICENSE
tagpatch-0.1.4.dist-info/RECORD
