Metadata-Version: 2.4
Name: tagpatch
Version: 0.1.4
Summary: CLI tool which applies common patches to music tags
Author-email: Anchit Bajaj <python.pypi@abifog.com>
License: MIT
License-File: LICENSE
Keywords: music,tag
Requires-Python: >=3.10
Requires-Dist: httpx>=0.28.1
Requires-Dist: music-tag>=0.4.3
Requires-Dist: mutagen>=1.47.0
Requires-Dist: tabulate>=0.9.0
Requires-Dist: typer==0.20.1
